setup.py
expect/__init__.py
expect.py.egg-info/PKG-INFO
expect.py.egg-info/SOURCES.txt
expect.py.egg-info/dependency_links.txt
expect.py.egg-info/top_level.txt