Metadata-Version: 2.1
Name: expect.py
Version: 0.121
Summary: My CMD 模組
Home-page: UNKNOWN
License: LGPL
Platform: UNKNOWN
